pixiedust_twitterdemo
