Metadata-Version: 1.0
Name: pixiedust-twitterdemo
Version: 0.2
Summary: Pixiedust demo of the Twitter Sentiment Analysis tutorials
Home-page: https://github.com/ibm-cds-labs/pixiedust_incubator/tree/master/twitterdemo
Author: David Taieb
Author-email: david_taieb@us.ibm.com
License: Apache 2.0
Platform: UNKNOWN
